faas_sa/__init__.py
faas_sa/api.py
faas_sa/faas_storage_agent_pb2.py
faas_sa/faas_storage_agent_pb2_grpc.py
faas_sa/test_server.py
faas_sa-0.1.0.dist-info/METADATA
faas_sa-0.1.0.dist-info/WHEEL
faas_sa-0.1.0.dist-info/top_level.txt
faas_sa-0.1.0.dist-info/RECORD
