Metadata-Version: 2.1
Name: faas-sa
Version: 0.1.0
Summary: Faas-storage-agent apis
Home-page: UNKNOWN
Author: why
Author-email: UNKNOWN
License: MIT
Platform: UNKNOWN
